ProxyPatternPool.py
proxypatternpool-11.6.dist-info/licenses/LICENSE
proxypatternpool-11.6.dist-info/METADATA
proxypatternpool-11.6.dist-info/WHEEL
proxypatternpool-11.6.dist-info/top_level.txt
proxypatternpool-11.6.dist-info/RECORD
