Metadata-Version: 2.4
Name: ProxyPatternPool
Version: 11.6
Summary: Generic Proxy and Pool Classes for Python
Author-email: Fabien Coelho <proxy.pool@coelho.net>
License-Expression: CC0-1.0
Project-URL: repository, https://github.com/zx80/proxy-pattern-pool
Project-URL: documentation, https://zx80.github.io/proxy-pattern-pool/
Project-URL: issues, https://github.com/zx80/proxy-pattern-pool/issues
Project-URL: package, https://pypi.org/project/ProxyPatternPool/
Classifier: Development Status :: 5 - Production/Stable
Classifier: Intended Audience :: Developers
Classifier: Programming Language :: Python
Classifier: Topic :: Software Development :: Libraries :: Python Modules
Requires-Python: >=3.10
License-File: LICENSE
Provides-Extra: local
Requires-Dist: werkzeug; extra == "local"
Requires-Dist: eventlet; extra == "local"
Requires-Dist: gevent; python_version < "3.13" and extra == "local"
Provides-Extra: dev
Requires-Dist: mypy; extra == "dev"
Requires-Dist: pyright; extra == "dev"
Requires-Dist: flake8; extra == "dev"
Requires-Dist: black; extra == "dev"
Requires-Dist: ruff; extra == "dev"
Requires-Dist: pytest; extra == "dev"
Requires-Dist: coverage; extra == "dev"
Requires-Dist: pymarkdownlnt; extra == "dev"
Provides-Extra: doc
Requires-Dist: mkdocs; extra == "doc"
Requires-Dist: mkdocs-material; extra == "doc"
Requires-Dist: mkdocstrings[python]; extra == "doc"
Provides-Extra: pub
Requires-Dist: build; extra == "pub"
Requires-Dist: wheel; extra == "pub"
Requires-Dist: twine; extra == "pub"
Dynamic: license-file
